honeybee_standards/__init__.py
honeybee_standards/energy_default.json
honeybee_standards/radiance_default.json
honeybee_standards/constructions/user_library.idf
honeybee_standards/constructions/user_library.json
honeybee_standards/constructionsets/user_library.json
honeybee_standards/modifiers/user_library.json
honeybee_standards/modifiers/user_library.mat
honeybee_standards/modifiersets/user_library.json
honeybee_standards/programtypes/user_library.json
honeybee_standards/schedules/user_library.idf
honeybee_standards/schedules/user_library.json
honeybee_standards-2.0.5.dist-info/LICENSE
honeybee_standards-2.0.5.dist-info/METADATA
honeybee_standards-2.0.5.dist-info/WHEEL
honeybee_standards-2.0.5.dist-info/top_level.txt
honeybee_standards-2.0.5.dist-info/RECORD
