Metadata-Version: 2.1
Name: honeybee-standards
Version: 2.0.5
Summary: Default standards and templates used throughout honeybee extensions.
Home-page: https://github.com/ladybug-tools/honeybee-standards
Author: Ladybug Tools
Author-email: info@ladybug.tools
License: UNKNOWN
Platform: UNKNOWN
Classifier: Programming Language :: Python :: 2.7
Classifier: Programming Language :: Python :: 3.6
Classifier: Programming Language :: Python :: Implementation :: CPython
Classifier: License :: OSI Approved :: GNU General Public License v3 (GPLv3)
Classifier: Operating System :: OS Independent
License-File: LICENSE
